clippings2anki/__init__.py
clippings2anki/__main__.py
clippings2anki/anki.py
clippings2anki/clippings.py
clippings2anki/flashcards.py
clippings2anki/gui.py
clippings2anki-0.2.1.dist-info/METADATA
clippings2anki-0.2.1.dist-info/WHEEL
clippings2anki-0.2.1.dist-info/licenses/LICENSE.md
clippings2anki-0.2.1.dist-info/RECORD
