Metadata-Version: 2.1
Name: clippings2anki
Version: 0.2.1
Summary: clippings2anki
Project-URL: Homepage, https://github.com/bewuwy/kindle-clippings-anki-exporter
Project-URL: Bug Tracker, https://github.com/bewuwy/kindle-clippings-anki-exporter/issues
Author-email: bewu <bewu@bewu.dev>
License-File: LICENSE.md
Classifier: License :: OSI Approved :: MIT License
Classifier: Operating System :: OS Independent
Classifier: Programming Language :: Python :: 3
Requires-Python: >=3.7
Requires-Dist: pyqt6
Requires-Dist: tqdm
Requires-Dist: wiktionaryparser
